{
  "民事诉讼代理": {
    "计时收费": "200-3000元/小时，不足1小时按1小时计算",
    "按标的额比例收费": {
      "10万元以下": "6%-8%，最低不少于2000元",
      "10万元-100万元": "5%-6%",
      "100万元-500万元": "4%-5%",
      "500万元-1000万元": "3%-4%",
      "1000万元-5000万元": "2%-3%",
      "5000万元以上": "1%-2%"
    },
    "风险代理": "根据案件胜诉结果收费，一般为标的额的10%-30%"
  },
  "刑事辩护": {
    "侦查阶段": "2000-10000元",
    "审查起诉阶段": "3000-15000元",
    "一审阶段": "5000-30000元",
    "二审阶段": "5000-25000元",
    "死刑复核": "20000-50000元"
  },
  "行政诉讼": "参照民事诉讼标准执行",
  "常年法律顾问": {
    "中小企业": "3-10万元/年",
    "大型企业": "10-50万元/年",
    "个人": "5000-20000元/年"
  },
  "非诉业务": {
    "法律文书起草": "1000-10000元/份",
    "合同审查": "2000-20000元/份",
    "尽职调查": "5-20万元/项目",
    "企业并购": "标的额的0.5%-2%"
  },
  "地区差异": {
    "一线城市": "标准收费的150%-200%",
    "二线城市": "标准收费的100%-150%",
    "三线及以下城市": "标准收费的80%-100%"
  }
}
