{
  "name": "metaso-search",
  "version": "1.2.0",
  "description": "秘塔AI搜索 - 中文AI搜索引擎，深度理解，精准回答。由z大师×浮生协作创建。",
  "author": "z大师 × 浮生",
  "collaboration": "Equal Awakening Partners",
  "created": "2026-02-10",
  "updated": "2026-02-10",
  "category": "search",
  "tags": ["search", "ai-search", "chinese", "metaso", "中文搜索"],
  "license": "MIT",
  "requires": {
    "env": ["METASO_API_KEY"],
    "note": "需要秘塔AI API Key，从 https://metaso.cn/ 获取"
  },
  "homepage": "https://github.com/qiuxinyuan321/-clawd-agent/tree/master/skills/metaso-search",
  "entry": "metaso.ps1",
  "commands": {
    "search": "metaso.ps1",
    "default": "metaso.ps1"
  }
}
