{
  "owner": "ykforerlang",
  "slug": "data-charts-visualization",
  "displayName": "Lightweight charting skill: powerful styling & direct PNG export",
  "latest": {
    "version": "1.0.13",
    "publishedAt": 1776182448535,
    "commit": "https://github.com/openclaw/skills/commit/65e7bd253dab9237b1423dfb4032d4fa790324f2"
  },
  "history": [
    {
      "version": "1.0.8",
      "publishedAt": 1776086756277,
      "commit": "https://github.com/openclaw/skills/commit/f7ba0b367ec4898b4df6ca3bda8c52b09c1b0ca9"
    }
  ]
}
