{
  "cicatrix": "scar",
  "cicatrices": "scar",
  "hypertrophic scar": "hypertrophic scar",
  "infantile hemangioma": "infantile hemangioma",
  "hemangioma": "hemangioma",
  "propranolol": "propranolol",
  "pulsed dye laser": "pulsed dye laser",
  "PDL": "pulsed dye laser",
  "fractional laser": "fractional laser",
  "laser": "laser",
  "collagen": "collagen",
  "fibroblast": "fibroblast",
  "angiogenesis": "angiogenesis",
  "TGF-beta": "TGF-beta",
  "TGF-β": "TGF-beta",
  "TGF-beta1": "TGF-beta1",
  "TGF-β1": "TGF-beta1",
  "keloid": "keloid"
}
