{
  "name": "receipt-manager",
  "version": "1.0.0",
  "description": "Receipt management skill - automatically extract and archive receipts from chat images",
  "trigger": ["receipt", "收据", "发票", "expense", "报销", "花费", "消费", "报销"],
  "author": "clinch",
  "handler": "python3 scripts/handler.py",
  "commands": {
    "add": "python3 scripts/receipt_db.py add",
    "search": "python3 scripts/receipt_db.py search",
    "summary": "python3 scripts/receipt_db.py summary",
    "list": "python3 scripts/receipt_db.py list"
  }
}
