{
  "weapons": [
    {
      "id": "青龙偃月刀",
      "owner": "关羽",
      "type": "大刀",
      "rarity": "传说",
      "stats": {"攻击": 95, "重量": "极重"},
      "skill": "拖刀计 / 青龙出水",
      "lore": "重八十二斤，唯关羽能舞动"
    },
    {
      "id": "丈八蛇矛",
      "owner": "张飞",
      "type": "长矛",
      "rarity": "传说",
      "stats": {"攻击": 90, "突刺": 98},
      "skill": "当阳桥吼 / 蛇矛旋击",
      "lore": "张飞喝退曹军百万的兵器"
    },
    {
      "id": "方天画戟",
      "owner": "吕布",
      "type": "戟",
      "rarity": "传说",
      "stats": {"攻击": 99, "范围": "中"},
      "skill": "辕门射戟 / 天下无双",
      "lore": "天下第一武将吕布的专属战戟"
    },
    {
      "id": "倚天剑",
      "owner": "曹操",
      "type": "剑",
      "rarity": "史诗",
      "stats": {"攻击": 75, "速度": 88},
      "skill": "令行天下 / 斩将夺旗",
      "lore": "曹操随身佩剑，象征天子权威"
    },
    {
      "id": "雌雄双股剑",
      "owner": "刘备",
      "type": "双剑",
      "rarity": "史诗",
      "stats": {"攻击": 70, "速度": 85, "气势": 90},
      "skill": "仁义双刃 / 以德服人",
      "lore": "刘备年轻时所用，体现仁德之道"
    },
    {
      "id": "长坂坡枪",
      "owner": "赵云",
      "type": "长枪",
      "rarity": "传说",
      "stats": {"攻击": 93, "速度": 97},
      "skill": "单骑救主 / 七进七出",
      "lore": "赵云百万军中如入无人之境"
    },
    {
      "id": "诸葛连弩",
      "owner": "诸葛亮",
      "type": "机械弩",
      "rarity": "传说",
      "stats": {"攻击": 85, "射程": 99, "连射": 10},
      "skill": "箭雨如注 / 连环机关",
      "lore": "诸葛亮发明，一次可射十箭"
    },
    {
      "id": "普通铁剑",
      "type": "剑",
      "rarity": "普通",
      "stats": {"攻击": 35},
      "skill": null,
      "lore": "新手初始武器"
    }
  ],

  "mounts": [
    {
      "id": "赤兔马",
      "owner": "吕布→关羽",
      "speed": 100,
      "stamina": 95,
      "rarity": "传说",
      "ability": "日行千里，冲锋时攻击+30%",
      "lore": "天下第一名马，'人中吕布，马中赤兔'"
    },
    {
      "id": "的卢马",
      "owner": "刘备",
      "speed": 90,
      "stamina": 99,
      "rarity": "史诗",
      "ability": "危急时刻触发「绝境飞跃」——跃过河流障碍",
      "lore": "檀溪一跃，救刘备于危难"
    },
    {
      "id": "绝影",
      "owner": "曹操",
      "speed": 95,
      "stamina": 90,
      "rarity": "史诗",
      "ability": "箭矢回避率+25%",
      "lore": "曹操最爱的战马，官渡中箭仍奔驰"
    },
    {
      "id": "普通战马",
      "speed": 60,
      "stamina": 70,
      "rarity": "普通",
      "ability": null,
      "lore": "标准军马，新兵标配"
    }
  ],

  "war_machines": [
    {
      "id": "投石车",
      "type": "攻城器械",
      "damage": "建筑破坏高",
      "range": "远程",
      "crew": 8,
      "weakness": "移动慢，怕火攻",
      "lore": "攻城必备，官渡曹操大量使用"
    },
    {
      "id": "冲车",
      "type": "攻城器械",
      "damage": "城门破坏极高",
      "range": "近战",
      "crew": 20,
      "weakness": "城墙弓箭",
      "lore": "撞击城门，正面强攻利器"
    },
    {
      "id": "木牛流马",
      "type": "运输器械",
      "function": "运输粮草，不需人力",
      "speed": "山地可用",
      "rarity": "传说",
      "creator": "诸葛亮",
      "lore": "诸葛亮发明的自动运粮装置，司马懿无法仿制"
    },
    {
      "id": "连环战船",
      "type": "水战器械",
      "function": "多船铁链相连，稳定性高",
      "weakness": "火攻时无法逃脱",
      "lore": "赤壁之战曹操失败的关键——周瑜火攻"
    },
    {
      "id": "孔明灯（信号版）",
      "type": "通讯器械",
      "function": "夜间传递军事信号",
      "creator": "诸葛亮",
      "lore": "用于传达撤退或进攻信号"
    },
    {
      "id": "八卦阵",
      "type": "阵法",
      "function": "困敌于阵中，敌军迷失方向",
      "creator": "诸葛亮",
      "weakness": "需要熟悉阵法者才能破解",
      "lore": "陆逊差点困死于此，靠黄承彦引路脱出"
    }
  ],

  "items": [
    {
      "id": "青囊书",
      "type": "医术秘籍",
      "effect": "学习后可救治重伤，治愈率+50%",
      "owner": "华佗",
      "rarity": "传说",
      "lore": "华佗医术精华，可惜被曹操烧毁"
    },
    {
      "id": "锦囊妙计",
      "type": "计策道具",
      "effect": "危急时刻开启，获得一次脱险机会",
      "creator": "诸葛亮",
      "rarity": "史诗",
      "single_use": true,
      "lore": "诸葛亮预判未来所书，刘备三个锦囊入东吴"
    },
    {
      "id": "虎符",
      "type": "军事令牌",
      "effect": "持有者可调动对应军队",
      "rarity": "史诗",
      "lore": "兵权象征，失虎符则失军权"
    },
    {
      "id": "传国玉玺",
      "type": "政治道具",
      "effect": "持有者可宣称正统，外交+30，但成为天下公敌",
      "rarity": "传说",
      "lore": "孙坚发现，袁术称帝用，最终害了袁术"
    },
    {
      "id": "离间信",
      "type": "谍报道具",
      "effect": "使用后目标武将与主公信任度-40",
      "rarity": "稀有",
      "single_use": true,
      "lore": "反间计必备，赤壁之战周瑜反间曹操"
    }
  ],

  "ultimate_skills": [
    {
      "id": "温酒斩华雄",
      "owner": "关羽",
      "type": "武将必杀",
      "effect": "单挑必胜（敌方武力<90时），士气暴涨",
      "trigger": "温酒未凉之前（限时10回合内）",
      "lore": "诸侯会盟，关羽请战，温酒未凉已取华雄首级"
    },
    {
      "id": "长坂七进七出",
      "owner": "赵云",
      "type": "武将必杀",
      "effect": "无视包围，穿越敌阵，救出指定人物",
      "cooldown": "一战一次",
      "lore": "长坂坡独闯曹营，救出阿斗"
    },
    {
      "id": "草船借箭",
      "owner": "诸葛亮",
      "type": "谋士必杀",
      "effect": "己方箭矢+10万，敌方箭矢消耗-10万",
      "condition": "需大雾天气",
      "lore": "向曹操借箭十万，三日完成"
    },
    {
      "id": "借东风",
      "owner": "诸葛亮",
      "type": "谋士必杀",
      "effect": "改变当日风向，火攻威力×3",
      "cooldown": "全局一次",
      "lore": "赤壁之战关键——周瑜缺东风，诸葛亮登坛祈风"
    },
    {
      "id": "当阳桥断后",
      "owner": "张飞",
      "type": "武将必杀",
      "effect": "喝退敌军追兵（敌方统帅<80时），己方全员撤退成功",
      "lore": "张飞独立当阳桥，一声断喝退曹军"
    },
    {
      "id": "空城计",
      "owner": "诸葛亮",
      "type": "谋士必杀",
      "effect": "敌方疑兵，取消本轮进攻（对司马懿无效）",
      "condition": "兵力差距悬殊时才能触发",
      "lore": "城内无兵，诸葛亮抚琴退司马懿十五万大军"
    },
    {
      "id": "火烧赤壁",
      "owner": "周瑜+黄盖",
      "type": "联合必杀",
      "effect": "水战中摧毁敌方连环战船，造成全军30%损失",
      "condition": "需东风+连环船+苦肉计三个条件同时满足",
      "lore": "三国最著名的以少胜多战役"
    },
    {
      "id": "过五关斩六将",
      "owner": "关羽",
      "type": "武将必杀",
      "effect": "突破封锁，强行通过任意关卡",
      "condition": "单人行动时可触发",
      "lore": "关羽护送嫂夫人寻刘备，连斩曹操六将"
    }
  ],

  "relationships": {
    "sworn_brothers": [
      {"group": "桃园三结义", "members": ["刘备", "关羽", "张飞"], "bond": "义比天高，死生相随"}
    ],
    "rivals": [
      {"pair": ["曹操", "刘备"], "type": "政敌+惺惺相惜", "quote": "天下英雄，唯使君与操耳"},
      {"pair": ["诸葛亮", "司马懿"], "type": "毕生对手", "quote": "既生瑜，何生亮（实为周瑜叹）"}
    ],
    "mentor_student": [
      {"master": "水镜先生", "students": ["诸葛亮", "庞统"]},
      {"master": "诸葛亮", "students": ["姜维"]}
    ],
    "betrayals": [
      {"betrayer": "吕布", "betrayed": ["丁原", "董卓"], "reason": "赤兔马+金银财宝"},
      {"betrayer": "吕蒙", "betrayed": "关羽", "note": "白衣渡江，袭取荆州"}
    ]
  }
}
